chatgraph/__init__.py
chatgraph/auth/credentials.py
chatgraph/bot/chatbot_model.py
chatgraph/bot/chatbot_router.py
chatgraph/bot/default_functions.py
chatgraph/cli/__init__.py
chatgraph/container/container.py
chatgraph/error/chatbot_error.py
chatgraph/error/route_error.py
chatgraph/gRPC/gRPCCall.py
chatgraph/logger/logger.py
chatgraph/messages/message_consumer.py
chatgraph/models/actions.py
chatgraph/models/message.py
chatgraph/models/userstate.py
chatgraph/pb/router.proto
chatgraph/pb/router_pb2.py
chatgraph/pb/router_pb2_grpc.py
chatgraph/services/__init__.py
chatgraph/services/router_http_client.py
chatgraph/types/background_task.py
chatgraph/types/end_types.py
chatgraph/types/route.py
chatgraph/types/usercall.py
chatgraph-1.0.6.dist-info/METADATA
chatgraph-1.0.6.dist-info/WHEEL
chatgraph-1.0.6.dist-info/licenses/LICENSE
chatgraph-1.0.6.dist-info/RECORD
