Metadata-Version: 2.4
Name: chatgraph
Version: 1.0.6
Summary: A user-friendly chatbot library
Project-URL: Homepage, https://github.com/irissonnlima/chatgraph
Project-URL: Repository, https://github.com/irissonnlima/chatgraph
Author-email: "Irisson N. Lima" <irisson.lima@verdecard.com.br>
License: MIT
License-File: LICENSE
Keywords: chatbot,chatgraph,messaging,python,rabbitmq,routing
Requires-Python: <4.0,>=3.12
Requires-Dist: aio-pika>=9.5.8
Requires-Dist: grpcio-tools>=1.67.0
Requires-Dist: grpcio>=1.67.0
Requires-Dist: httpx>=0.28.1
Requires-Dist: matplotlib>=3.10.0
Requires-Dist: networkx>=3.4.2
Requires-Dist: pika>=1.3.2
Requires-Dist: protobuf>=6.31.1
Requires-Dist: python-dotenv>=1.0.1
Requires-Dist: rich>=13.8.1
Requires-Dist: typer>=0.12.5
